pyinla-0.1.3.dist-info/RECORD
pyinla-0.1.3.dist-info/WHEEL
pyinla-0.1.3.dist-info/entry_points.txt
pyinla-0.1.3.dist-info/top_level.txt
pyinla-0.1.3.dist-info/METADATA
pyinla/marginal_utils.c
pyinla/scale_model.c
pyinla/collect.c
pyinla/inla_call.cpython-311-darwin.so
pyinla/qinv.c
pyinla/collect.cpython-311-darwin.so
pyinla/surv.c
pyinla/pc_bym.c
pyinla/pyinla_report.cpython-311-darwin.so
pyinla/_safety.c
pyinla/sm.cpython-311-darwin.so
pyinla/models.c
pyinla/control_defaults.cpython-311-darwin.so
pyinla/sections.cpython-311-darwin.so
pyinla/_api.cpython-311-darwin.so
pyinla/qinv.cpython-311-darwin.so
pyinla/os.py
pyinla/__init__.py
pyinla/sm.c
pyinla/binary.c
pyinla/control_defaults.c
pyinla/read_graph.cpython-311-darwin.so
pyinla/pyinla_report.c
pyinla/_api.c
pyinla/rprior.cpython-311-darwin.so
pyinla/rprior.c
pyinla/inla_call.c
pyinla/utils.c
pyinla/surv.cpython-311-darwin.so
pyinla/utils.cpython-311-darwin.so
pyinla/sections.c
pyinla/scale_model.cpython-311-darwin.so
pyinla/binary.cpython-311-darwin.so
pyinla/read_graph.c
pyinla/models.cpython-311-darwin.so
pyinla/create_data_file.cpython-311-darwin.so
pyinla/_safety.cpython-311-darwin.so
pyinla/pc_bym.cpython-311-darwin.so
pyinla/options.cpython-311-darwin.so
pyinla/marginal_utils.cpython-311-darwin.so
pyinla/fmesher_io.py
pyinla/create_data_file.c
pyinla/binary_manager.py
pyinla/options.c
pyinla/model_defs/transforms.py
pyinla/model_defs/latent.py
pyinla/model_defs/__init__.py
pyinla/model_defs/other_sections.py
pyinla/model_defs/likelihood.py
pyinla/fmesher/pyproject.toml
pyinla/fmesher/__init__.py
pyinla/fmesher/core.py
pyinla/fmesher/mesh.py
pyinla/fmesher/README.md
pyinla/fmesher/example.py
pyinla/fmesher/spde.py
pyinla/fmesher/exceptions.py
pyinla/fmesher/install.py
